<?xml version="1.0" encoding="utf-8" ?>
<Acciones>
  <Accion>
    <ruta> PELICULAS PORTADS\ACCION\111.jpg</ruta>
  </Accion>
  <Accion>
    <ruta>PELICULAS PORTADS\ACCION\11SPIDERMAN.jpg </ruta>
  </Accion>
  <Accion>
    <ruta>PELICULAS PORTADS\ACCION\1BABY.jpg </ruta>
  </Accion>
  <Accion>
    <ruta> PELICULAS PORTADS\ACCION\AMENAZA.jpg</ruta>
  </Accion>
  <Accion>
    <ruta> PELICULAS PORTADS\ACCION\BAYWATR.jpg</ruta>
  </Accion>
  <Accion>
    <ruta> PELICULAS PORTADS\ACCION\CASABLANCA.jpg</ruta>
  </Accion>
  <Accion>
    <ruta>PELICULAS PORTADS\ACCION\COLLOSAL.jpg </ruta>
  </Accion>
  <Accion>
    <ruta>PELICULAS PORTADS\ACCION\CTROOS.jpg </ruta>
  </Accion>
  <Accion>
    <ruta>PELICULAS PORTADS\ACCION\D13.jpg </ruta>
  </Accion>
  <Accion>
    <ruta>PELICULAS PORTADS\ACCION\EL GUARDAESPALDAS.jpg</ruta>
  </Accion>
  <Accion>
    <ruta>PELICULAS PORTADS\ACCION\EL ULTIMO REY.jpg </ruta>
  </Accion>
  <Accion>
    <ruta>PELICULAS PORTADS\ACCION\FEARLESS.jpg</ruta>
  </Accion>
  <Accion>
    <ruta>PELICULAS PORTADS\ACCION\GHOST.jpg </ruta>
  </Accion>
  <Accion>
    <ruta>PELICULAS PORTADS\ACCION\GODZILLA.jpg</ruta>
  </Accion>
  <Accion>
    <ruta>PELICULAS PORTADS\ACCION\GUARDIANES.jpg</ruta>
  </Accion>
  <Accion>
    <ruta>PELICULAS PORTADS\ACCION\JUEGO.jpg </ruta>
  </Accion>
  <Accion>
    <ruta>PELICULAS PORTADS\ACCION\LEGO BAT.jpg </ruta>
  </Accion>
  <Accion>
    <ruta>PELICULAS PORTADS\ACCION\MARINE 5.jpg </ruta>
  </Accion>
  <Accion>
    <ruta>PELICULAS PORTADS\ACCION\MOMIA.jpg </ruta>
  </Accion>
  <Accion>
    <ruta>PELICULAS PORTADS\ACCION\MUJER MARA.jpg </ruta>
  </Accion>
  <Accion>
    <ruta>PELICULAS PORTADS\ACCION\PANDEMIC.jpg </ruta>
  </Accion>
  <Accion>
    <ruta>PELICULAS PORTADS\ACCION\PIRATASCARIBE.jpg </ruta>
  </Accion>
  <Accion>
    <ruta>PELICULAS PORTADS\ACCION\RUNNER.jpg </ruta>
  </Accion>
  <Accion>
    <ruta>PELICULAS PORTADS\ACCION\SECRUTITY.jpg </ruta>
  </Accion>
  <Accion>
    <ruta> PELICULAS PORTADS\ACCION\SNK.jpg</ruta>
  </Accion>
  <Accion>
    <ruta>PELICULAS PORTADS\ACCION\SNK2.jpg </ruta>
  </Accion>
  <Accion>
    <ruta>PELICULAS PORTADS\ACCION\SWATR.jpg </ruta>
  </Accion>
  <Accion>
    <ruta> PELICULAS PORTADS\ACCION\TAXI.jpg</ruta>
  </Accion>
  <Accion>
    <ruta>PELICULAS PORTADS\ACCION\TEKKEN.jpg </ruta>
  </Accion>
  <Accion>
    <ruta> PELICULAS PORTADS\ACCION\THOR.jpg</ruta>
  </Accion>
  <Accion>
    <ruta>PELICULAS PORTADS\ACCION\TORRE OSCURA.jpg </ruta>
  </Accion>
  <Accion>
    <ruta>PELICULAS PORTADS\ACCION\TRASNSFORM.jpg </ruta>
  </Accion>
  <Accion>
    <ruta>PELICULAS PORTADS\ACCION\VOLCANO.jpg </ruta>
  </Accion>
  <Accion>
    <ruta>PELICULAS PORTADS\ACCION\WENDY.jpg </ruta>
  </Accion>
  <Accion>
    <ruta>PELICULAS PORTADS\ACCION\WHELLMAN.jpg</ruta>
  </Accion>

  <Accion>
    <ruta>PELICULAS PORTADS\ACCION\XXX.jpg </ruta>
  </Accion>
  

</Acciones>